run.py
jaxgcrl/__init__.py
jaxgcrl/agents/__init__.py
jaxgcrl/agents/crl/__init__.py
jaxgcrl/agents/crl/crl.py
jaxgcrl/agents/crl/losses.py
jaxgcrl/agents/crl/networks.py
jaxgcrl/agents/ppo/__init__.py
jaxgcrl/agents/ppo/ppo.py
jaxgcrl/agents/sac/__init__.py
jaxgcrl/agents/sac/networks.py
jaxgcrl/agents/sac/sac.py
jaxgcrl/agents/td3/__init__.py
jaxgcrl/agents/td3/losses.py
jaxgcrl/agents/td3/networks.py
jaxgcrl/agents/td3/td3.py
jaxgcrl/envs/__init__.py
jaxgcrl/envs/ant.py
jaxgcrl/envs/ant_ball.py
jaxgcrl/envs/ant_ball_maze.py
jaxgcrl/envs/ant_maze.py
jaxgcrl/envs/ant_push.py
jaxgcrl/envs/half_cheetah.py
jaxgcrl/envs/humanoid.py
jaxgcrl/envs/humanoid_maze.py
jaxgcrl/envs/pusher.py
jaxgcrl/envs/pusher2.py
jaxgcrl/envs/reacher.py
jaxgcrl/envs/simple_maze.py
jaxgcrl/envs/wrappers.py
jaxgcrl/envs/assets/ant.xml
jaxgcrl/envs/assets/ant_ball.xml
jaxgcrl/envs/assets/ant_maze.xml
jaxgcrl/envs/assets/ant_push.xml
jaxgcrl/envs/assets/half_cheetah.xml
jaxgcrl/envs/assets/humanoid.xml
jaxgcrl/envs/assets/humanoid_maze.xml
jaxgcrl/envs/assets/panda_binpick_easy.xml
jaxgcrl/envs/assets/panda_binpick_easy_EEF.xml
jaxgcrl/envs/assets/panda_binpick_hard.xml
jaxgcrl/envs/assets/panda_grasp.xml
jaxgcrl/envs/assets/panda_push_easy.xml
jaxgcrl/envs/assets/panda_push_hard.xml
jaxgcrl/envs/assets/panda_reach.xml
jaxgcrl/envs/assets/pusher2.xml
jaxgcrl/envs/assets/simple_maze.xml
jaxgcrl/envs/assets/franka_emika_panda/assets/finger_0.obj
jaxgcrl/envs/assets/franka_emika_panda/assets/finger_1.obj
jaxgcrl/envs/assets/franka_emika_panda/assets/hand.stl
jaxgcrl/envs/assets/franka_emika_panda/assets/hand_0.obj
jaxgcrl/envs/assets/franka_emika_panda/assets/hand_1.obj
jaxgcrl/envs/assets/franka_emika_panda/assets/hand_2.obj
jaxgcrl/envs/assets/franka_emika_panda/assets/hand_3.obj
jaxgcrl/envs/assets/franka_emika_panda/assets/hand_4.obj
jaxgcrl/envs/assets/franka_emika_panda/assets/link0.stl
jaxgcrl/envs/assets/franka_emika_panda/assets/link0_0.obj
jaxgcrl-0.2.8.dist-info/licenses/LICENSE
jaxgcrl-0.2.8.dist-info/METADATA
jaxgcrl-0.2.8.dist-info/WHEEL
jaxgcrl-0.2.8.dist-info/entry_points.txt
jaxgcrl-0.2.8.dist-info/top_level.txt
jaxgcrl-0.2.8.dist-info/RECORD
