Metadata-Version: 2.4
Name: jaxgcrl
Version: 0.2.8
Summary: Blazingly fast goal-conditioned environments based on MJX and BRAX.
Project-URL: homepage, https://michalbortkiewicz.github.io/JaxGCRL/
Requires-Python: >=3.10
License-File: LICENSE
Requires-Dist: pip>=25.0.1
Requires-Dist: jax==0.4.25
Requires-Dist: jaxlib==0.4.25+cuda12.cudnn89; platform_system == "Linux"
Requires-Dist: nvidia-cudnn-cu11<9.0,>=8.9; platform_system == "Linux"
Requires-Dist: nvidia-cuda-cupti-cu12>=12.4; platform_system == "Linux"
Requires-Dist: nvidia-cusolver-cu12>=11.7.3.90; platform_system == "Linux"
Requires-Dist: jaxlib==0.4.25; platform_system != "Linux"
Requires-Dist: flax>=0.8.3
Requires-Dist: brax>=0.12.1
Requires-Dist: matplotlib==3.8.4
Requires-Dist: mujoco==3.2.7
Requires-Dist: mujoco-mjx==3.2.7
Requires-Dist: numpy<2
Requires-Dist: scipy>=1.12
Requires-Dist: tyro>=0.9.16
Requires-Dist: wandb
Requires-Dist: wandb-osh
Dynamic: license-file
